idp_layout_spec/__init__.py
idp_layout_spec/coordinate.py
idp_layout_spec/enums.py
idp_layout_spec/file.py
idp_layout_spec/text.py
idp_layout_spec/utils/__init__.py
idp_layout_spec/utils/calc.py
idp_layout_spec-0.1.4.dist-info/WHEEL
idp_layout_spec-0.1.4.dist-info/METADATA
idp_layout_spec-0.1.4.dist-info/RECORD
